MANIFEST.in
README.txt
setup.py
XStatic_Leaflet_MarkerCluster.egg-info/PKG-INFO
XStatic_Leaflet_MarkerCluster.egg-info/SOURCES.txt
XStatic_Leaflet_MarkerCluster.egg-info/dependency_links.txt
XStatic_Leaflet_MarkerCluster.egg-info/namespace_packages.txt
XStatic_Leaflet_MarkerCluster.egg-info/not-zip-safe
XStatic_Leaflet_MarkerCluster.egg-info/requires.txt
XStatic_Leaflet_MarkerCluster.egg-info/top_level.txt
xstatic/__init__.py
xstatic/pkg/__init__.py
xstatic/pkg/leaflet_markercluster/__init__.py
xstatic/pkg/leaflet_markercluster/data/MarkerCluster.Default.css
xstatic/pkg/leaflet_markercluster/data/MarkerCluster.css
xstatic/pkg/leaflet_markercluster/data/WhereAreTheJavascriptFiles.txt
xstatic/pkg/leaflet_markercluster/data/leaflet.markercluster-src.js
xstatic/pkg/leaflet_markercluster/data/leaflet.markercluster-src.js.map
xstatic/pkg/leaflet_markercluster/data/leaflet.markercluster.js
xstatic/pkg/leaflet_markercluster/data/leaflet.markercluster.js.map