Metadata-Version: 1.2
Name: XStatic-Leaflet-MarkerCluster
Version: 1.4.1.1
Summary: Leaflet-MarkerCluster 1.4.1 (XStatic packaging standard)
Home-page: https://github.com/Leaflet/Leaflet.markercluster
Maintainer: Serghei Mihai
Maintainer-email: smihai@entrouvert.com
License: (same as Leaflet-MarkerCluster)
Keywords: leaflet_markercluster xstatic
Platform: any
